easy_db3-1.1.0.dist-info/licenses/LICENSE
easydb/__init__.py
easydb/easydb.py
easy_db3-1.1.0.dist-info/METADATA
easy_db3-1.1.0.dist-info/WHEEL
easy_db3-1.1.0.dist-info/top_level.txt
easy_db3-1.1.0.dist-info/RECORD
